microsoft_auth/.gitignore
microsoft_auth/__init__.py
microsoft_auth/admin.py
microsoft_auth/apps.py
microsoft_auth/backends.py
microsoft_auth/client.py
microsoft_auth/conf.py
microsoft_auth/context_processors.py
microsoft_auth/models.py
microsoft_auth/urls.py
microsoft_auth/utils.py
microsoft_auth/views.py
microsoft_auth/migrations/0001_initial.py
microsoft_auth/migrations/0002_fix_microsoft_id_length.py
microsoft_auth/migrations/0003_microsoft_id_openid.py
microsoft_auth/migrations/__init__.py
microsoft_auth/static/microsoft/css/login.css
microsoft_auth/static/microsoft/js/login.js
microsoft_auth/templates/microsoft/admin_login.html
microsoft_auth/templates/microsoft/auth_callback.html
django_microsoft_auth-3.0.1.dist-info/AUTHORS.rst
django_microsoft_auth-3.0.1.dist-info/LICENSE
django_microsoft_auth-3.0.1.dist-info/METADATA
django_microsoft_auth-3.0.1.dist-info/WHEEL
django_microsoft_auth-3.0.1.dist-info/top_level.txt
django_microsoft_auth-3.0.1.dist-info/RECORD
