Metadata-Version: 2.1
Name: django-microsoft-auth
Version: 3.0.1
Summary: Simple app to enable Microsoft Account, Office 365 and Xbox Live authentcation as a Django authentcation backend.
Author-email: Christopher Bailey <cbailey@mort.is>
License: 
Project-URL: Documentation, https://django-microsoft-auth.readthedocs.io/en/latest/
Project-URL: Source, https://github.com/AngellusMortis/django_microsoft_auth
Keywords: django_microsoft_auth
Classifier: Development Status :: 5 - Production/Stable
Classifier: Intended Audience :: Developers
Classifier: License :: OSI Approved :: MIT License
Classifier: Natural Language :: English
Classifier: Programming Language :: Python :: 3
Classifier: Programming Language :: Python :: 3.8
Classifier: Programming Language :: Python :: 3.9
Classifier: Programming Language :: Python :: 3.10
Classifier: Framework :: Django :: 3.2
Classifier: Framework :: Django :: 4.0
Classifier: Framework :: Django :: 4.1
Requires-Python: >=3.8
Provides-Extra: dev
Provides-Extra: ql
License-File: LICENSE
License-File: AUTHORS.rst
